rtl/axi4lite_mem.v
`timescale 1ns / 1ps

module axi4lite_mem #(
    parameter integer ADDR_WIDTH = 12               // 4 KB => 1024 cuvinte
)(
    input  wire                   clk,
    input  wire                   rst_n,

    // ---- port CPU (citire asincrona, scriere sincrona) ----
    input  wire [31:0]            imem_addr,
    output wire [31:0]            imem_rdata,
    input  wire [31:0]            dmem_addr,
    input  wire [31:0]            dmem_wdata,
    input  wire [3:0]             dmem_wstrb,
    input  wire                   dmem_we,
    output wire [31:0]            dmem_rdata,

    // ---- port AXI4-Lite slave (PS) ----
    input  wire [ADDR_WIDTH-1:0]  s_axi_awaddr,
    input  wire [2:0]             s_axi_awprot,
    input  wire                   s_axi_awvalid,
    output wire                   s_axi_awready,
    input  wire [31:0]            s_axi_wdata,
    input  wire [3:0]             s_axi_wstrb,
    input  wire                   s_axi_wvalid,
    output wire                   s_axi_wready,
    output wire [1:0]             s_axi_bresp,
    output wire                   s_axi_bvalid,
    input  wire                   s_axi_bready,
    input  wire [ADDR_WIDTH-1:0]  s_axi_araddr,
    input  wire [2:0]             s_axi_arprot,
    input  wire                   s_axi_arvalid,
    output wire                   s_axi_arready,
    output wire [31:0]            s_axi_rdata,
    output wire [1:0]             s_axi_rresp,
    output wire                   s_axi_rvalid,
    input  wire                   s_axi_rready
);

    localparam integer IDX_HI = ADDR_WIDTH - 1;      // bit superior index cuvant
    localparam integer WORDS  = (1 << (ADDR_WIDTH - 2));
    reg [31:0] mem [0:WORDS-1];

    // index de cuvant (adresa pe octeti, /4)
    wire [ADDR_WIDTH-3:0] imem_idx = imem_addr[IDX_HI:2];
    wire [ADDR_WIDTH-3:0] dmem_idx = dmem_addr[IDX_HI:2];

    // ---- port CPU: citiri asincrone ----
    assign imem_rdata = mem[imem_idx];
    assign dmem_rdata = mem[dmem_idx];

    // ============================================================
    //  AXI4-Lite: canal de SCRIERE
    // ============================================================
    reg                  awready_r, wready_r, bvalid_r;
    // acceptam adresa si datele impreuna (AXI4-Lite simplu)
    wire wr_accept = ~awready_r & s_axi_awvalid & s_axi_wvalid & ~bvalid_r;
    wire [ADDR_WIDTH-3:0] axi_waddr_idx = s_axi_awaddr[IDX_HI:2];

    always @(posedge clk or negedge rst_n) begin
        if (!rst_n) begin
            awready_r <= 1'b0; wready_r <= 1'b0; bvalid_r <= 1'b0;
        end else begin
            awready_r <= wr_accept;          // puls de 1 ciclu
            wready_r  <= wr_accept;
            if (wr_accept)                     bvalid_r <= 1'b1;
            else if (bvalid_r & s_axi_bready)  bvalid_r <= 1'b0;
        end
    end

    assign s_axi_awready = awready_r;
    assign s_axi_wready  = wready_r;
    assign s_axi_bvalid  = bvalid_r;
    assign s_axi_bresp   = 2'b00;

    // ============================================================
    //  AXI4-Lite: canal de CITIRE
    // ============================================================
    reg                  arready_r, rvalid_r;
    reg [31:0]           rdata_r;
    wire rd_accept = ~arready_r & s_axi_arvalid & ~rvalid_r;

    always @(posedge clk or negedge rst_n) begin
        if (!rst_n) begin
            arready_r <= 1'b0; rvalid_r <= 1'b0; rdata_r <= 32'b0;
        end else begin
            arready_r <= rd_accept;
            if (rd_accept) begin
                rdata_r  <= mem[s_axi_araddr[IDX_HI:2]];
                rvalid_r <= 1'b1;
            end else if (rvalid_r & s_axi_rready) begin
                rvalid_r <= 1'b0;
            end
        end
    end

    assign s_axi_arready = arready_r;
    assign s_axi_rdata   = rdata_r;
    assign s_axi_rvalid  = rvalid_r;
    assign s_axi_rresp   = 2'b00;

    // ============================================================
    //  SCRIERE in memorie: CPU (dmem_we) sau AXI (wr_accept), cu strobe.
    //  In uz normal sunt excluse temporal (CPU in reset cat incarca PS).
    // ============================================================
    always @(posedge clk) begin
        if (dmem_we) begin
            if (dmem_wstrb[0]) mem[dmem_idx][7:0]   <= dmem_wdata[7:0];
            if (dmem_wstrb[1]) mem[dmem_idx][15:8]  <= dmem_wdata[15:8];
            if (dmem_wstrb[2]) mem[dmem_idx][23:16] <= dmem_wdata[23:16];
            if (dmem_wstrb[3]) mem[dmem_idx][31:24] <= dmem_wdata[31:24];
        end
        if (wr_accept) begin
            if (s_axi_wstrb[0]) mem[axi_waddr_idx][7:0]   <= s_axi_wdata[7:0];
            if (s_axi_wstrb[1]) mem[axi_waddr_idx][15:8]  <= s_axi_wdata[15:8];
            if (s_axi_wstrb[2]) mem[axi_waddr_idx][23:16] <= s_axi_wdata[23:16];
            if (s_axi_wstrb[3]) mem[axi_waddr_idx][31:24] <= s_axi_wdata[31:24];
        end
    end

endmodule

test/tb_axi4lite.v
`timescale 1ns / 1ps
// ============================================================
//  tb_axi4lite.v  -  BFM master AXI4-Lite pentru axi4lite_mem
// ------------------------------------------------------------
//  Verifica: scriere AXI, citire AXI, raspunsuri OKAY, byte-strobe,
//  si accesul prin portul CPU (back-door) la aceeasi memorie.
// ============================================================
`ifndef DUMP_FILE
 `define DUMP_FILE "waveform/tb_axi4lite.vcd"
`endif

module tb_axi4lite;

    localparam ADDR_WIDTH = 12;
    reg clk = 1'b0, rst_n;
    integer errors = 0;
    always #5 clk = ~clk;

    reg  [ADDR_WIDTH-1:0] awaddr, araddr;
    reg  [31:0]           wdata;
    reg  [3:0]            wstrb;
    reg                   awvalid, wvalid, bready, arvalid, rready;
    wire                  awready, wready, bvalid, arready, rvalid;
    wire [1:0]            bresp, rresp;
    wire [31:0]           rdata;

    reg  [31:0] imem_addr, dmem_addr, dmem_wdata;
    reg  [3:0]  dmem_wstrb;
    reg         dmem_we;
    wire [31:0] imem_rdata, dmem_rdata;

    axi4lite_mem #(.ADDR_WIDTH(ADDR_WIDTH)) dut (
        .clk(clk), .rst_n(rst_n),
        .imem_addr(imem_addr), .imem_rdata(imem_rdata),
        .dmem_addr(dmem_addr), .dmem_wdata(dmem_wdata), .dmem_wstrb(dmem_wstrb),
        .dmem_we(dmem_we), .dmem_rdata(dmem_rdata),
        .s_axi_awaddr(awaddr), .s_axi_awprot(3'b0), .s_axi_awvalid(awvalid), .s_axi_awready(awready),
        .s_axi_wdata(wdata), .s_axi_wstrb(wstrb), .s_axi_wvalid(wvalid), .s_axi_wready(wready),
        .s_axi_bresp(bresp), .s_axi_bvalid(bvalid), .s_axi_bready(bready),
        .s_axi_araddr(araddr), .s_axi_arprot(3'b0), .s_axi_arvalid(arvalid), .s_axi_arready(arready),
        .s_axi_rdata(rdata), .s_axi_rresp(rresp), .s_axi_rvalid(rvalid), .s_axi_rready(rready)
    );

    // ---- scriere AXI4-Lite (faza adresa/date, apoi faza raspuns) ----
    task axi_write;
        input [ADDR_WIDTH-1:0] addr;
        input [31:0]           data;
        input [3:0]            strb;
        begin
            @(negedge clk);
            awaddr = addr; wdata = data; wstrb = strb;
            awvalid = 1'b1; wvalid = 1'b1;
            do @(posedge clk); while (!(awready && wready));
            @(negedge clk); awvalid = 1'b0; wvalid = 1'b0;
            bready = 1'b1;                       // bready inainte de a astepta bvalid
            do @(posedge clk); while (!bvalid);  // se stinge la acest front (bvalid&bready)
            if (bresp !== 2'b00) begin
                errors = errors + 1; $display("  FAIL: BRESP=%b la addr=%h", bresp, addr);
            end
            @(negedge clk); bready = 1'b0;
        end
    endtask

    // ---- citire AXI4-Lite ----
    task axi_read;
        input  [ADDR_WIDTH-1:0] addr;
        output [31:0]           data;
        begin
            @(negedge clk);
            araddr = addr; arvalid = 1'b1;
            do @(posedge clk); while (!arready);
            @(negedge clk); arvalid = 1'b0;
            rready = 1'b1;                        // ready abia in faza R
            do @(posedge clk); while (!rvalid);   // slave-ul tine rvalid pana la rready
            data = rdata;
            if (rresp !== 2'b00) begin
                errors = errors + 1; $display("  FAIL: RRESP=%b la addr=%h", rresp, addr);
            end
            @(negedge clk); rready = 1'b0;
        end
    endtask

    task chk; input integer id; input [31:0] got, exp; begin
        if (got !== exp) begin
            errors = errors + 1;
            $display("  FAIL test %0d: got=%h exp=%h", id, got, exp);
        end
    end endtask

    // watchdog: nu lasa simularea sa atarne
    initial begin #50000; $display("[AXI4LITE] >>> FAIL <<< (TIMEOUT)"); $finish; end

    reg [31:0] rd;
    initial begin
        $dumpfile(`DUMP_FILE);
        $dumpvars(0, tb_axi4lite);
        $display("[AXI4LITE] pornire teste...");
        awvalid=0; wvalid=0; bready=0; arvalid=0; rready=0;
        awaddr=0; araddr=0; wdata=0; wstrb=0;
        imem_addr=0; dmem_addr=0; dmem_wdata=0; dmem_wstrb=0; dmem_we=0;
        rst_n = 1'b0; @(negedge clk); @(negedge clk); rst_n = 1'b1; @(negedge clk);

        // 1) scriere + citire AXI
        axi_write(12'h000, 32'hDEADBEEF, 4'hF);
        axi_write(12'h004, 32'h12345678, 4'hF);
        axi_read (12'h000, rd); chk(1, rd, 32'hDEADBEEF);
        axi_read (12'h004, rd); chk(2, rd, 32'h12345678);

        // 2) PS scrie program -> CPU il citeste prin portul de instructiuni
        axi_write(12'h010, 32'h00A00093, 4'hF);
        @(negedge clk); imem_addr = 32'h010;
        @(negedge clk); chk(3, imem_rdata, 32'h00A00093);

        // 3) CPU scrie (store) -> PS citeste prin AXI
        @(negedge clk);
        dmem_addr = 32'h020; dmem_wdata = 32'hCAFEF00D; dmem_wstrb = 4'hF; dmem_we = 1'b1;
        @(negedge clk); dmem_we = 1'b0;
        axi_read(12'h020, rd); chk(4, rd, 32'hCAFEF00D);

        // 4) byte-strobe
        axi_write(12'h030, 32'h00000000, 4'hF);
        axi_write(12'h030, 32'h0000AB00, 4'b0010);
        axi_read (12'h030, rd); chk(5, rd, 32'h0000AB00);
        axi_write(12'h030, 32'hFF000000, 4'b1000);
        axi_read (12'h030, rd); chk(6, rd, 32'hFF00AB00);

        if (errors == 0) $display("[AXI4LITE] >>> PASS <<< (protocol AXI4-Lite + back-door CPU OK)");
        else             $display("[AXI4LITE] >>> FAIL <<< (%0d erori)", errors);
        $finish;
    end

endmodule

waveform/tb_axi4lite.vcd
$date
	Thu Jun 11 04:51:17 2026
$end
$version
	Icarus Verilog
$end
$timescale
	1ps
$end
$scope module tb_axi4lite $end
$var wire 2 ! bresp [1:0] $end
$var wire 2 " rresp [1:0] $end
$var wire 1 # wready $end
$var wire 1 $ rvalid $end
$var wire 32 % rdata [31:0] $end
$var wire 32 & imem_rdata [31:0] $end
$var wire 32 ' dmem_rdata [31:0] $end
$var wire 1 ( bvalid $end
$var wire 1 ) awready $end
$var wire 1 * arready $end
$var parameter 32 + ADDR_WIDTH $end
$var reg 12 , araddr [11:0] $end
$var reg 1 - arvalid $end
$var reg 12 . awaddr [11:0] $end
$var reg 1 / awvalid $end
$var reg 1 0 bready $end
$var reg 1 1 clk $end
$var reg 32 2 dmem_addr [31:0] $end
$var reg 32 3 dmem_wdata [31:0] $end
$var reg 1 4 dmem_we $end
$var reg 4 5 dmem_wstrb [3:0] $end
$var reg 32 6 imem_addr [31:0] $end
$var reg 32 7 rd [31:0] $end
$var reg 1 8 rready $end
$var reg 1 9 rst_n $end
$var reg 32 : wdata [31:0] $end
$var reg 4 ; wstrb [3:0] $end
$var reg 1 < wvalid $end
$var integer 32 = errors [31:0] $end
$scope module dut $end
$var wire 1 1 clk $end
$var wire 32 > dmem_addr [31:0] $end
$var wire 32 ? dmem_rdata [31:0] $end
$var wire 32 @ dmem_wdata [31:0] $end
$var wire 1 4 dmem_we $end
$var wire 4 A dmem_wstrb [3:0] $end
$var wire 32 B imem_addr [31:0] $end
$var wire 32 C imem_rdata [31:0] $end
$var wire 1 D rd_accept $end
$var wire 1 9 rst_n $end
$var wire 12 E s_axi_araddr [11:0] $end
$var wire 3 F s_axi_arprot [2:0] $end
$var wire 1 * s_axi_arready $end
$var wire 1 - s_axi_arvalid $end
$var wire 12 G s_axi_awaddr [11:0] $end
$var wire 3 H s_axi_awprot [2:0] $end
$var wire 1 ) s_axi_awready $end
$var wire 1 / s_axi_awvalid $end
$var wire 1 0 s_axi_bready $end
$var wire 2 I s_axi_bresp [1:0] $end
$var wire 1 ( s_axi_bvalid $end
$var wire 32 J s_axi_rdata [31:0] $end
$var wire 1 8 s_axi_rready $end
$var wire 2 K s_axi_rresp [1:0] $end
$var wire 1 $ s_axi_rvalid $end
$var wire 32 L s_axi_wdata [31:0] $end
$var wire 1 # s_axi_wready $end
$var wire 4 M s_axi_wstrb [3:0] $end
$var wire 1 < s_axi_wvalid $end
$var wire 1 N wr_accept $end
$var wire 10 O imem_idx [9:0] $end
$var wire 10 P dmem_idx [9:0] $end
$var wire 10 Q axi_waddr_idx [9:0] $end
$var parameter 32 R ADDR_WIDTH $end
$var parameter 32 S IDX_HI $end
$var parameter 32 T WORDS $end
$var reg 1 U arready_r $end
$var reg 1 V awready_r $end
$var reg 1 W bvalid_r $end
$var reg 32 X rdata_r [31:0] $end
$var reg 1 Y rvalid_r $end
$var reg 1 Z wready_r $end
$upscope $end
$scope task axi_read $end
$var reg 12 [ addr [11:0] $end
$var reg 32 \ data [31:0] $end
$upscope $end
$scope task axi_write $end
$var reg 12 ] addr [11:0] $end
$var reg 32 ^ data [31:0] $end
$var reg 4 _ strb [3:0] $end
$upscope $end
$scope task chk $end
$var reg 32 ` exp [31:0] $end
$var reg 32 a got [31:0] $end
$var integer 32 b id [31:0] $end
$upscope $end
$upscope $end
$enddefinitions $end
$comment Show the parameter values. $end
$dumpall
b10000000000 T
b1011 S
b1100 R
b1100 +
$end
#0
$dumpvars
bx b
bx a
bx `
bx _
bx ^
bx ]
bx \
bx [
0Z
0Y
b0 X
0W
0V
0U
b0 Q
b0 P
b0 O
0N
b0 M
b0 L
b0 K
b0 J
b0 I
b0 H
b0 G
b0 F
b0 E
0D
bx C
b0 B
b0 A
b0 @
bx ?
b0 >
b0 =
0<
b0 ;
b0 :
09
08
bx 7
b0 6
b0 5
04
b0 3
b0 2
01
00
0/
b0 .
0-
b0 ,
0*
0)
0(
bx '
bx &
b0 %
0$
0#
b0 "
b0 !
$end
#5000
11
#10000
01
#15000
11
#20000
19
01
#25000
11
#30000
b1111 _
b11011110101011011011111011101111 ^
b0 ]
01
#35000
11
#40000
1N
1<
1/
b1111 ;
b1111 M
b11011110101011011011111011101111 :
b11011110101011011011111011101111 L
01
#45000
0N
1(
1W
1#
1Z
1)
1V
b11011110101011011011111011101111 &
b11011110101011011011111011101111 C
b11011110101011011011111011101111 '
b11011110101011011011111011101111 ?
11
#50000
01
#55000
0#
0Z
0)
0V
11
#60000
10
0<
0/
01
#65000
0(
0W
11
#70000
b10010001101000101011001111000 ^
b100 ]
00
01
#75000
11
#80000
1N
b1 Q
1<
1/
b10010001101000101011001111000 :
b10010001101000101011001111000 L
b100 .
b100 G
01
#85000
0N
1(
1W
1#
1Z
1)
1V
11
#90000
01
#95000
0#
0Z
0)
0V
11
#100000
10
0<
0/
01
#105000
0(
0W
11
#110000
b0 [
00
01
#115000
11
#120000
1D
1-
01
#125000
0D
1$
1Y
b11011110101011011011111011101111 %
b11011110101011011011111011101111 J
b11011110101011011011111011101111 X
1*
1U
11
#130000
01
#135000
0*
0U
11
#140000
18
0-
01
#145000
0$
0Y
b11011110101011011011111011101111 \
11
#150000
b100 [
b11011110101011011011111011101111 `
b11011110101011011011111011101111 a
b1 b
b11011110101011011011111011101111 7
08
01
#155000
11
#160000
1D
1-
b100 ,
b100 E
01
#165000
0D
1$
1Y
b10010001101000101011001111000 %
b10010001101000101011001111000 J
b10010001101000101011001111000 X
1*
1U
11
#170000
01
#175000
0*
0U
11
#180000
18
0-
01
#185000
0$
0Y
b10010001101000101011001111000 \
11
#190000
b101000000000000010010011 ^
b10000 ]
b10010001101000101011001111000 `
b10010001101000101011001111000 a
b10 b
b10010001101000101011001111000 7
08
01
#195000
11
#200000
1N
b100 Q
1<
1/
b101000000000000010010011 :
b101000000000000010010011 L
b10000 .
b10000 G
01
#205000
0N
1(
1W
1#
1Z
1)
1V
11
#210000
01
#215000
0#
0Z
0)
0V
11
#220000
10
0<
0/
01
#225000
0(
0W
11
#230000
00
01
#235000
11
#240000
b101000000000000010010011 &
b101000000000000010010011 C
b100 O
b10000 6
b10000 B
01
#245000
11
#250000
b101000000000000010010011 `
b101000000000000010010011 a
b11 b
01
#255000
11
#260000
bx '
bx ?
b1000 P
14
b1111 5
b1111 A
b11001010111111101111000000001101 3
b11001010111111101111000000001101 @
b100000 2
b100000 >
01
#265000
b11001010111111101111000000001101 '
b11001010111111101111000000001101 ?
11
#270000
b100000 [
04
01
#275000
11
#280000
1D
1-
b100000 ,
b100000 E
01
#285000
0D
1$
1Y
b11001010111111101111000000001101 %
b11001010111111101111000000001101 J
b11001010111111101111000000001101 X
1*
1U
11
#290000
01
#295000
0*
0U
11
#300000
18
0-
01
#305000
0$
0Y
b11001010111111101111000000001101 \
11
#310000
b0 ^
b110000 ]
b11001010111111101111000000001101 `
b11001010111111101111000000001101 a
b100 b
b11001010111111101111000000001101 7
08
01
#315000
11
#320000
1N
b1100 Q
1<
1/
b0 :
b0 L
b110000 .
b110000 G
01
#325000
0N
1(
1W
1#
1Z
1)
1V
11
#330000
01
#335000
0#
0Z
0)
0V
11
#340000
10
0<
0/
01
#345000
0(
0W
11
#350000
b10 _
b1010101100000000 ^
00
01
#355000
11
#360000
1N
1<
1/
b10 ;
b10 M
b1010101100000000 :
b1010101100000000 L
01
#365000
0N
1(
1W
1#
1Z
1)
1V
11
#370000
01
#375000
0#
0Z
0)
0V
11
#380000
10
0<
0/
01
#385000
0(
0W
11
#390000
b110000 [
00
01
#395000
11
#400000
1D
1-
b110000 ,
b110000 E
01
#405000
0D
1$
1Y
b1010101100000000 %
b1010101100000000 J
b1010101100000000 X
1*
1U
11
#410000
01
#415000
0*
0U
11
#420000
18
0-
01
#425000
0$
0Y
b1010101100000000 \
11
#430000
b1000 _
b11111111000000000000000000000000 ^
b1010101100000000 `
b1010101100000000 a
b101 b
b1010101100000000 7
08
01
#435000
11
#440000
1N
1<
1/
b1000 ;
b1000 M
b11111111000000000000000000000000 :
b11111111000000000000000000000000 L
01
#445000
0N
1(
1W
1#
1Z
1)
1V
11
#450000
01
#455000
0#
0Z
0)
0V
11
#460000
10
0<
0/
01
#465000
0(
0W
11
#470000
00
01
#475000
11
#480000
1D
1-
01
#485000
0D
1$
1Y
b11111111000000001010101100000000 %
b11111111000000001010101100000000 J
b11111111000000001010101100000000 X
1*
1U
11
#490000
01
#495000
0*
0U
11
#500000
18
0-
01
#505000
0$
0Y
b11111111000000001010101100000000 \
11
#510000
b11111111000000001010101100000000 `
b11111111000000001010101100000000 a
b110 b
b11111111000000001010101100000000 7
08
01
