rtl/riscv_defs.vh
`ifndef RISCV_DEFS_VH
`define RISCV_DEFS_VH

// ------------------------------------------------------------
//  Parametri generali
// ------------------------------------------------------------
`define XLEN         32                 // latimea cuvantului
`define RV_NOP       32'h0000_0013      // addi x0, x0, 0  (bula in pipeline)
`define RESET_PC     32'h0000_0000      // adresa de start dupa reset

// ------------------------------------------------------------
//  Extractoare de campuri din instructiune (i = vector 32-bit)
//    Formate RISC-V:
//      R: funct7 | rs2 | rs1 | funct3 | rd | opcode
//      I: imm[11:0]       | rs1 | funct3 | rd | opcode
//      S: imm[11:5] | rs2 | rs1 | funct3 | imm[4:0] | opcode
//      B: imm[12|10:5]|rs2|rs1|funct3| imm[4:1|11] | opcode
//      U: imm[31:12]                  | rd | opcode
//      J: imm[20|10:1|11|19:12]       | rd | opcode
// ------------------------------------------------------------
`define OPCODE(i)    (i[6:0])
`define RD(i)        (i[11:7])
`define RS1(i)       (i[19:15])
`define RS2(i)       (i[24:20])
`define FUNCT3(i)    (i[14:12])
`define FUNCT7(i)    (i[31:25])

// ------------------------------------------------------------
//  Opcode-uri (bitii [6:0])
// ------------------------------------------------------------
`define OPC_LUI      7'b0110111         // U  - load upper immediate
`define OPC_AUIPC    7'b0010111         // U  - add upper imm to PC
`define OPC_JAL      7'b1101111         // J  - jump and link
`define OPC_JALR     7'b1100111         // I  - jump and link register
`define OPC_BRANCH   7'b1100011         // B  - branch conditionat
`define OPC_LOAD     7'b0000011         // I  - load din memorie
`define OPC_STORE    7'b0100011         // S  - store in memorie
`define OPC_OP_IMM   7'b0010011         // I  - ALU cu immediate
`define OPC_OP       7'b0110011         // R  - ALU cu registre (+ extensia M)
`define OPC_MISC_MEM 7'b0001111         // I  - FENCE
`define OPC_SYSTEM   7'b1110011         // I  - ECALL/EBREAK/CSR

// ------------------------------------------------------------
//  funct3 pentru OP / OP-IMM (aritmetica/logica)
//    SUB vs ADD si SRA vs SRL se disting prin bitul funct7[5] (=i[30])
// ------------------------------------------------------------
`define F3_ADD_SUB   3'b000             // ADD/ADDI ; SUB (funct7[5]=1)
`define F3_SLL       3'b001             // shift left logic
`define F3_SLT       3'b010             // set less than (cu semn)
`define F3_SLTU      3'b011             // set less than (fara semn)
`define F3_XOR       3'b100
`define F3_SRL_SRA   3'b101             // SRL ; SRA (funct7[5]=1)
`define F3_OR        3'b110
`define F3_AND       3'b111

// ------------------------------------------------------------
//  funct3 pentru BRANCH
// ------------------------------------------------------------
`define F3_BEQ       3'b000
`define F3_BNE       3'b001
`define F3_BLT       3'b100
`define F3_BGE       3'b101
`define F3_BLTU      3'b110
`define F3_BGEU      3'b111

// ------------------------------------------------------------
//  funct3 pentru LOAD / STORE (dimensiunea accesului)
// ------------------------------------------------------------
`define F3_LB        3'b000             // load byte (cu semn)
`define F3_LH        3'b001             // load half (cu semn)
`define F3_LW        3'b010             // load word
`define F3_LBU       3'b100             // load byte (fara semn)
`define F3_LHU       3'b101             // load half (fara semn)

`define F3_SB        3'b000             // store byte
`define F3_SH        3'b001             // store half
`define F3_SW        3'b010             // store word

// ------------------------------------------------------------
//  funct7 relevante
// ------------------------------------------------------------
`define F7_BASE      7'b0000000         // ADD, SRL, AND, ...
`define F7_ALT       7'b0100000         // SUB, SRA  (bitul [5]=1)
`define F7_MULDIV    7'b0000001         // extensia M
`define F7_BIT5      30                 // pozitia bitului ALT in instructiune

// ------------------------------------------------------------
//  Extensia M (opcode OPC_OP, funct7 = F7_MULDIV), prin funct3
// ------------------------------------------------------------
`define F3_MUL       3'b000             // produs, 32 bitii inferiori
`define F3_MULH      3'b001             // produs sup., semnat x semnat
`define F3_MULHSU    3'b010             // produs sup., semnat x nesemnat
`define F3_MULHU     3'b011             // produs sup., nesemnat x nesemnat
`define F3_DIV       3'b100             // impartire cu semn
`define F3_DIVU      3'b101             // impartire fara semn
`define F3_REM       3'b110             // rest cu semn
`define F3_REMU      3'b111             // rest fara semn

// ------------------------------------------------------------
//  funct3 pentru SYSTEM (ECALL/EBREAK + CSR)
// ------------------------------------------------------------
`define F3_PRIV      3'b000             // ECALL/EBREAK (dupa funct12)
`define F3_CSRRW     3'b001
`define F3_CSRRS     3'b010
`define F3_CSRRC     3'b011
`define F3_CSRRWI    3'b101
`define F3_CSRRSI    3'b110
`define F3_CSRRCI    3'b111

// ------------------------------------------------------------
//  funct12 (instr[31:20]) pentru SYSTEM cu funct3=000
// ------------------------------------------------------------
`define SYS_ECALL    12'h000
`define SYS_EBREAK   12'h001
`define SYS_MRET     12'h302

// ------------------------------------------------------------
//  Adrese CSR (mod masina) - subset minim pentru Zicsr + trap
// ------------------------------------------------------------
`define CSR_MSTATUS  12'h300
`define CSR_MISA     12'h301
`define CSR_MIE      12'h304
`define CSR_MTVEC    12'h305
`define CSR_MSCRATCH 12'h340
`define CSR_MEPC     12'h341
`define CSR_MCAUSE   12'h342
`define CSR_MTVAL    12'h343
`define CSR_MIP      12'h344
`define CSR_MVENDORID 12'hF11
`define CSR_MARCHID   12'hF12
`define CSR_MIMPID    12'hF13
`define CSR_MHARTID   12'hF14

//  misa pentru RV32IM: MXL=01 (32b) | I (bit8) | M (bit12)
`define MISA_RV32IM  32'h40001100

// ------------------------------------------------------------
//  Cauze de trap (mcause, bitul de interrupt = 0 pentru exceptii)
// ------------------------------------------------------------
`define CAUSE_ILLEGAL    32'd2
`define CAUSE_BREAKPOINT 32'd3
`define CAUSE_ECALL_M    32'd11

// ------------------------------------------------------------
//  Encodarea interna a operatiei ALU (semnal de control, 4 biti)
//    Nu face parte din ISA - e conventia noastra interna.
// ------------------------------------------------------------
`define ALU_OP_W     4
`define ALU_ADD      4'b0000
`define ALU_SUB      4'b0001
`define ALU_SLL      4'b0010
`define ALU_SLT      4'b0011            // set-less-than cu semn
`define ALU_SLTU     4'b0100            // set-less-than fara semn
`define ALU_XOR      4'b0101
`define ALU_SRL      4'b0110
`define ALU_SRA      4'b0111
`define ALU_OR       4'b1000
`define ALU_AND      4'b1001
`define ALU_COPY_B   4'b1010            // trece operandul B (pentru LUI)
`define ALU_NOP      4'b1111            // fara efect (bula)

// ------------------------------------------------------------
//  Selectorul de tip immediate (semnal de control, intern)
//    Spune lui imm_gen din ce format sa extraga immediate-ul.
// ------------------------------------------------------------
`define IMM_SEL_W    3
`define IMM_I        3'd0               // OP-IMM, LOAD, JALR
`define IMM_S        3'd1               // STORE
`define IMM_B        3'd2               // BRANCH
`define IMM_U        3'd3               // LUI, AUIPC
`define IMM_J        3'd4               // JAL

// ------------------------------------------------------------
//  Selectorul sursei de writeback (ce se scrie in registrul rd)
// ------------------------------------------------------------
`define WB_SEL_W     2
`define WB_ALU       2'd0               // rezultatul ALU
`define WB_MEM       2'd1               // data citita din memorie (load)
`define WB_PC4       2'd2               // PC+4 (adresa de retur, jal/jalr)

// ------------------------------------------------------------
//  Coduri pentru unitatea de forwarding (Faza 4)
//    Selecteaza sursa operandului ALU in etapa EX.
// ------------------------------------------------------------
`define FWD_NONE     2'b00              // din ID/EX (register file)
`define FWD_EXMEM    2'b10              // din EX/MEM (instr. precedenta)
`define FWD_MEMWB    2'b01              // din MEM/WB (cu 2 instr. inainte)

`endif  // RISCV_DEFS_VH

rtl/csr.v
`timescale 1ns / 1ps
`include "riscv_defs.vh"

module csr (
    input  wire        clk,
    input  wire        rst_n,
    // acces CSR (din EX)
    input  wire        rd_en,
    input  wire        wr_en,
    input  wire [11:0] addr,
    input  wire [31:0] wdata,
    output reg  [31:0] rdata,
    output reg         addr_valid,
    // eveniment trap / mret (din EX)
    input  wire        trap_en,
    input  wire [31:0] trap_cause,
    input  wire [31:0] trap_epc,
    input  wire [31:0] trap_val,
    input  wire        mret_en,
    // iesiri spre redirectarea PC-ului
    output wire [31:0] mtvec_o,
    output wire [31:0] mepc_o
);

    // ---- registri de stare (campurile relevante) ----
    reg        mstatus_mie, mstatus_mpie;
    reg [31:0] mtvec, mscratch, mepc, mcause, mtval, mie, mip;

    // mstatus reconstituit: MIE=bit3, MPIE=bit7, MPP=bits[12:11]=11
    wire [31:0] mstatus = {19'b0, 2'b11, 4'b0, mstatus_mpie, 3'b0, mstatus_mie, 3'b0};

    assign mtvec_o = {mtvec[31:2], 2'b00};   // mod direct
    assign mepc_o  = mepc;

    always @(*) begin
        addr_valid = 1'b1;
        case (addr)
            `CSR_MSTATUS : rdata = mstatus;
            `CSR_MISA    : rdata = `MISA_RV32IM;
            `CSR_MIE     : rdata = mie;
            `CSR_MTVEC   : rdata = mtvec;
            `CSR_MSCRATCH: rdata = mscratch;
            `CSR_MEPC    : rdata = mepc;
            `CSR_MCAUSE  : rdata = mcause;
            `CSR_MTVAL   : rdata = mtval;
            `CSR_MIP     : rdata = mip;
            `CSR_MVENDORID,
            `CSR_MARCHID,
            `CSR_MIMPID,
            `CSR_MHARTID : rdata = 32'b0;
            default      : begin rdata = 32'b0; addr_valid = 1'b0; end
        endcase
    end

    // ---- scriere / actualizare la trap / mret ----
    always @(posedge clk or negedge rst_n) begin
        if (!rst_n) begin
            mstatus_mie <= 1'b0; mstatus_mpie <= 1'b0;
            mtvec <= 32'b0; mscratch <= 32'b0; mepc <= 32'b0;
            mcause <= 32'b0; mtval <= 32'b0; mie <= 32'b0; mip <= 32'b0;
        end else if (trap_en) begin
            mepc        <= trap_epc;
            mcause      <= trap_cause;
            mtval       <= trap_val;
            mstatus_mpie<= mstatus_mie;
            mstatus_mie <= 1'b0;
        end else if (mret_en) begin
            mstatus_mie <= mstatus_mpie;
            mstatus_mpie<= 1'b1;
        end else if (wr_en) begin
            case (addr)
                `CSR_MSTATUS : begin mstatus_mie <= wdata[3]; mstatus_mpie <= wdata[7]; end
                `CSR_MIE     : mie      <= wdata;
                `CSR_MTVEC   : mtvec    <= wdata;
                `CSR_MSCRATCH: mscratch <= wdata;
                `CSR_MEPC    : mepc     <= wdata;
                `CSR_MCAUSE  : mcause   <= wdata;
                `CSR_MTVAL   : mtval    <= wdata;
                `CSR_MIP     : mip      <= wdata;
                default      : ;
            endcase
        end
    end

endmodule

test/tb_csr.v
`timescale 1ns / 1ps
`include "riscv_defs.vh"
// ============================================================
//  tb_csr.v  -  Testbench pentru fisierul de CSR-uri + trap
// ============================================================
`ifndef DUMP_FILE
 `define DUMP_FILE "waveform/tb_csr.vcd"
`endif

module tb_csr;
    reg         clk = 0, rst_n;
    reg         rd_en, wr_en, trap_en, mret_en;
    reg  [11:0] addr;
    reg  [31:0] wdata, trap_cause, trap_epc, trap_val;
    wire [31:0] rdata, mtvec_o, mepc_o;
    wire        addr_valid;
    integer     errors = 0;
    always #5 clk = ~clk;

    csr dut (.clk(clk), .rst_n(rst_n), .rd_en(rd_en), .wr_en(wr_en),
             .addr(addr), .wdata(wdata), .rdata(rdata), .addr_valid(addr_valid),
             .trap_en(trap_en), .trap_cause(trap_cause), .trap_epc(trap_epc),
             .trap_val(trap_val), .mret_en(mret_en), .mtvec_o(mtvec_o), .mepc_o(mepc_o));

    task wr; input [11:0] a; input [31:0] d; begin
        @(negedge clk); addr=a; wdata=d; wr_en=1; @(negedge clk); wr_en=0; end
    endtask
    task rd_chk; input integer id; input [11:0] a; input [31:0] exp; begin
        @(negedge clk); addr=a; rd_en=1; #1;
        if (rdata !== exp) begin errors=errors+1; $display("  FAIL %0d: CSR %h = %h (astept %h)", id, a, rdata, exp); end
        rd_en=0; end
    endtask

    initial begin
        $dumpfile(`DUMP_FILE); $dumpvars(0, tb_csr);
        rd_en=0; wr_en=0; trap_en=0; mret_en=0; addr=0; wdata=0; trap_cause=0; trap_epc=0; trap_val=0;
        rst_n=0; @(negedge clk); @(negedge clk); rst_n=1;

        // citiri read-only
        rd_chk(1, `CSR_MISA, `MISA_RV32IM);
        rd_chk(2, `CSR_MHARTID, 32'd0);

        // scriere/citire
        wr(`CSR_MTVEC, 32'h0000_1240);  rd_chk(3, `CSR_MTVEC, 32'h0000_1240);
        wr(`CSR_MSCRATCH, 32'hDEAD_BEEF); rd_chk(4, `CSR_MSCRATCH, 32'hDEAD_BEEF);
        if (mtvec_o !== 32'h0000_1240) begin errors=errors+1; $display("  FAIL: mtvec_o=%h", mtvec_o); end

        // adresa inexistenta -> addr_valid=0
        @(negedge clk); addr=12'h7C0; rd_en=1; #1;
        if (addr_valid !== 1'b0) begin errors=errors+1; $display("  FAIL: addr_valid pt CSR inexistent"); end
        rd_en=0;

        // pune MIE=1 prin mstatus, apoi declanseaza trap
        wr(`CSR_MSTATUS, 32'h0000_0008);   // MIE=bit3
        @(negedge clk); trap_en=1; trap_cause=`CAUSE_ECALL_M; trap_epc=32'h0000_0080; trap_val=0;
        @(negedge clk); trap_en=0;
        rd_chk(5, `CSR_MEPC, 32'h0000_0080);
        rd_chk(6, `CSR_MCAUSE, `CAUSE_ECALL_M);
        if (mepc_o !== 32'h0000_0080) begin errors=errors+1; $display("  FAIL: mepc_o=%h", mepc_o); end
        // dupa trap: MIE=0, MPIE=1 (vechiul MIE)
        @(negedge clk); addr=`CSR_MSTATUS; rd_en=1; #1;
        if (rdata[3] !== 1'b0 || rdata[7] !== 1'b1) begin errors=errors+1; $display("  FAIL: mstatus dupa trap = %h", rdata); end
        rd_en=0;

        // MRET: MIE<-MPIE(=1), MPIE<-1
        @(negedge clk); mret_en=1; @(negedge clk); mret_en=0;
        @(negedge clk); addr=`CSR_MSTATUS; rd_en=1; #1;
        if (rdata[3] !== 1'b1) begin errors=errors+1; $display("  FAIL: MIE dupa mret = %b", rdata[3]); end
        rd_en=0;

        if (errors==0) $display("[CSR] >>> PASS <<< (CSR-uri + trap + mret corecte)");
        else           $display("[CSR] >>> FAIL <<< (%0d erori)", errors);
        $finish;
    end
endmodule

waveform/tb_csr.vcd
$date
	Thu Jun 11 04:51:18 2026
$end
$version
	Icarus Verilog
$end
$timescale
	1ps
$end
$scope module tb_csr $end
$var wire 32 ! rdata [31:0] $end
$var wire 32 " mtvec_o [31:0] $end
$var wire 32 # mepc_o [31:0] $end
$var wire 1 $ addr_valid $end
$var reg 12 % addr [11:0] $end
$var reg 1 & clk $end
$var reg 1 ' mret_en $end
$var reg 1 ( rd_en $end
$var reg 1 ) rst_n $end
$var reg 32 * trap_cause [31:0] $end
$var reg 1 + trap_en $end
$var reg 32 , trap_epc [31:0] $end
$var reg 32 - trap_val [31:0] $end
$var reg 32 . wdata [31:0] $end
$var reg 1 / wr_en $end
$var integer 32 0 errors [31:0] $end
$scope module dut $end
$var wire 12 1 addr [11:0] $end
$var wire 1 & clk $end
$var wire 32 2 mepc_o [31:0] $end
$var wire 1 ' mret_en $end
$var wire 1 ( rd_en $end
$var wire 1 ) rst_n $end
$var wire 32 3 trap_cause [31:0] $end
$var wire 1 + trap_en $end
$var wire 32 4 trap_epc [31:0] $end
$var wire 32 5 trap_val [31:0] $end
$var wire 32 6 wdata [31:0] $end
$var wire 1 / wr_en $end
$var wire 32 7 mtvec_o [31:0] $end
$var wire 32 8 mstatus [31:0] $end
$var reg 1 $ addr_valid $end
$var reg 32 9 mcause [31:0] $end
$var reg 32 : mepc [31:0] $end
$var reg 32 ; mie [31:0] $end
$var reg 32 < mip [31:0] $end
$var reg 32 = mscratch [31:0] $end
$var reg 1 > mstatus_mie $end
$var reg 1 ? mstatus_mpie $end
$var reg 32 @ mtval [31:0] $end
$var reg 32 A mtvec [31:0] $end
$var reg 32 B rdata [31:0] $end
$upscope $end
$scope task rd_chk $end
$var reg 12 C a [11:0] $end
$var reg 32 D exp [31:0] $end
$var integer 32 E id [31:0] $end
$upscope $end
$scope task wr $end
$var reg 12 F a [11:0] $end
$var reg 32 G d [31:0] $end
$upscope $end
$upscope $end
$enddefinitions $end
$comment Show the parameter values. $end
$dumpall
$end
#0
$dumpvars
bx G
bx F
bx E
bx D
bx C
b0 B
b0 A
b0 @
0?
0>
b0 =
b0 <
b0 ;
b0 :
b0 9
b11000000000000 8
b0 7
b0 6
b0 5
b0 4
b0 3
b0 2
b0 1
b0 0
0/
b0 .
b0 -
b0 ,
0+
b0 *
0)
0(
0'
0&
b0 %
0$
b0 #
b0 "
b0 !
$end
#5000
1&
#10000
0&
#15000
1&
#20000
b1000000000000000001000100000000 D
b1100000001 C
b1 E
1)
0&
#25000
1&
#30000
b1000000000000000001000100000000 !
b1000000000000000001000100000000 B
1$
1(
b1100000001 %
b1100000001 1
0&
#31000
b0 D
b111100010100 C
b10 E
0(
#35000
1&
#40000
b0 !
b0 B
1(
b111100010100 %
b111100010100 1
0&
#41000
b1001001000000 G
b1100000101 F
0(
#45000
1&
#50000
1/
b1001001000000 .
b1001001000000 6
b1100000101 %
b1100000101 1
0&
#55000
b1001001000000 !
b1001001000000 B
b1001001000000 "
b1001001000000 7
b1001001000000 A
1&
#60000
b1001001000000 D
b1100000101 C
b11 E
0/
0&
#65000
1&
#70000
1(
0&
#71000
b11011110101011011011111011101111 G
b1101000000 F
0(
#75000
1&
#80000
b0 !
b0 B
1/
b11011110101011011011111011101111 .
b11011110101011011011111011101111 6
b1101000000 %
b1101000000 1
0&
#85000
b11011110101011011011111011101111 !
b11011110101011011011111011101111 B
b11011110101011011011111011101111 =
1&
#90000
b11011110101011011011111011101111 D
b1101000000 C
b100 E
0/
0&
#95000
1&
#100000
1(
0&
#101000
0(
#105000
1&
#110000
0$
b0 !
b0 B
1(
b11111000000 %
b11111000000 1
0&
#111000
b1000 G
b1100000000 F
0(
#115000
1&
#120000
b11000000000000 !
b11000000000000 B
1$
1/
b1000 .
b1000 6
b1100000000 %
b1100000000 1
0&
#125000
b11000000001000 !
b11000000001000 B
b11000000001000 8
1>
1&
#130000
0/
0&
#135000
1&
#140000
b10000000 ,
b10000000 4
b1011 *
b1011 3
1+
0&
#145000
b11000010000000 !
b11000010000000 B
b11000010000000 8
0>
1?
b1011 9
b10000000 #
b10000000 2
b10000000 :
1&
#150000
b10000000 D
b1101000001 C
b101 E
0+
0&
#155000
1&
#160000
b10000000 !
b10000000 B
1(
b1101000001 %
b1101000001 1
0&
#161000
b1011 D
b1101000010 C
b110 E
0(
#165000
1&
#170000
b1011 !
b1011 B
1(
b1101000010 %
b1101000010 1
0&
#171000
0(
#175000
1&
#180000
b11000010000000 !
b11000010000000 B
1(
b1100000000 %
b1100000000 1
0&
#181000
0(
#185000
1&
#190000
1'
0&
#195000
b11000010001000 !
b11000010001000 B
b11000010001000 8
1>
1&
#200000
0'
0&
#205000
1&
#210000
1(
0&
#211000
0(
