rtl/riscv_defs.vh
`ifndef RISCV_DEFS_VH
`define RISCV_DEFS_VH

// ------------------------------------------------------------
//  Parametri generali
// ------------------------------------------------------------
`define XLEN         32                 // latimea cuvantului
`define RV_NOP       32'h0000_0013      // addi x0, x0, 0  (bula in pipeline)
`define RESET_PC     32'h0000_0000      // adresa de start dupa reset

// ------------------------------------------------------------
//  Extractoare de campuri din instructiune (i = vector 32-bit)
//    Formate RISC-V:
//      R: funct7 | rs2 | rs1 | funct3 | rd | opcode
//      I: imm[11:0]       | rs1 | funct3 | rd | opcode
//      S: imm[11:5] | rs2 | rs1 | funct3 | imm[4:0] | opcode
//      B: imm[12|10:5]|rs2|rs1|funct3| imm[4:1|11] | opcode
//      U: imm[31:12]                  | rd | opcode
//      J: imm[20|10:1|11|19:12]       | rd | opcode
// ------------------------------------------------------------
`define OPCODE(i)    (i[6:0])
`define RD(i)        (i[11:7])
`define RS1(i)       (i[19:15])
`define RS2(i)       (i[24:20])
`define FUNCT3(i)    (i[14:12])
`define FUNCT7(i)    (i[31:25])

// ------------------------------------------------------------
//  Opcode-uri (bitii [6:0])
// ------------------------------------------------------------
`define OPC_LUI      7'b0110111         // U  - load upper immediate
`define OPC_AUIPC    7'b0010111         // U  - add upper imm to PC
`define OPC_JAL      7'b1101111         // J  - jump and link
`define OPC_JALR     7'b1100111         // I  - jump and link register
`define OPC_BRANCH   7'b1100011         // B  - branch conditionat
`define OPC_LOAD     7'b0000011         // I  - load din memorie
`define OPC_STORE    7'b0100011         // S  - store in memorie
`define OPC_OP_IMM   7'b0010011         // I  - ALU cu immediate
`define OPC_OP       7'b0110011         // R  - ALU cu registre (+ extensia M)
`define OPC_MISC_MEM 7'b0001111         // I  - FENCE
`define OPC_SYSTEM   7'b1110011         // I  - ECALL/EBREAK/CSR

// ------------------------------------------------------------
//  funct3 pentru OP / OP-IMM (aritmetica/logica)
//    SUB vs ADD si SRA vs SRL se disting prin bitul funct7[5] (=i[30])
// ------------------------------------------------------------
`define F3_ADD_SUB   3'b000             // ADD/ADDI ; SUB (funct7[5]=1)
`define F3_SLL       3'b001             // shift left logic
`define F3_SLT       3'b010             // set less than (cu semn)
`define F3_SLTU      3'b011             // set less than (fara semn)
`define F3_XOR       3'b100
`define F3_SRL_SRA   3'b101             // SRL ; SRA (funct7[5]=1)
`define F3_OR        3'b110
`define F3_AND       3'b111

// ------------------------------------------------------------
//  funct3 pentru BRANCH
// ------------------------------------------------------------
`define F3_BEQ       3'b000
`define F3_BNE       3'b001
`define F3_BLT       3'b100
`define F3_BGE       3'b101
`define F3_BLTU      3'b110
`define F3_BGEU      3'b111

// ------------------------------------------------------------
//  funct3 pentru LOAD / STORE (dimensiunea accesului)
// ------------------------------------------------------------
`define F3_LB        3'b000             // load byte (cu semn)
`define F3_LH        3'b001             // load half (cu semn)
`define F3_LW        3'b010             // load word
`define F3_LBU       3'b100             // load byte (fara semn)
`define F3_LHU       3'b101             // load half (fara semn)

`define F3_SB        3'b000             // store byte
`define F3_SH        3'b001             // store half
`define F3_SW        3'b010             // store word

// ------------------------------------------------------------
//  funct7 relevante
// ------------------------------------------------------------
`define F7_BASE      7'b0000000         // ADD, SRL, AND, ...
`define F7_ALT       7'b0100000         // SUB, SRA  (bitul [5]=1)
`define F7_MULDIV    7'b0000001         // extensia M
`define F7_BIT5      30                 // pozitia bitului ALT in instructiune

// ------------------------------------------------------------
//  Extensia M (opcode OPC_OP, funct7 = F7_MULDIV), prin funct3
// ------------------------------------------------------------
`define F3_MUL       3'b000             // produs, 32 bitii inferiori
`define F3_MULH      3'b001             // produs sup., semnat x semnat
`define F3_MULHSU    3'b010             // produs sup., semnat x nesemnat
`define F3_MULHU     3'b011             // produs sup., nesemnat x nesemnat
`define F3_DIV       3'b100             // impartire cu semn
`define F3_DIVU      3'b101             // impartire fara semn
`define F3_REM       3'b110             // rest cu semn
`define F3_REMU      3'b111             // rest fara semn

// ------------------------------------------------------------
//  funct3 pentru SYSTEM (ECALL/EBREAK + CSR)
// ------------------------------------------------------------
`define F3_PRIV      3'b000             // ECALL/EBREAK (dupa funct12)
`define F3_CSRRW     3'b001
`define F3_CSRRS     3'b010
`define F3_CSRRC     3'b011
`define F3_CSRRWI    3'b101
`define F3_CSRRSI    3'b110
`define F3_CSRRCI    3'b111

// ------------------------------------------------------------
//  funct12 (instr[31:20]) pentru SYSTEM cu funct3=000
// ------------------------------------------------------------
`define SYS_ECALL    12'h000
`define SYS_EBREAK   12'h001
`define SYS_MRET     12'h302

// ------------------------------------------------------------
//  Adrese CSR (mod masina) - subset minim pentru Zicsr + trap
// ------------------------------------------------------------
`define CSR_MSTATUS  12'h300
`define CSR_MISA     12'h301
`define CSR_MIE      12'h304
`define CSR_MTVEC    12'h305
`define CSR_MSCRATCH 12'h340
`define CSR_MEPC     12'h341
`define CSR_MCAUSE   12'h342
`define CSR_MTVAL    12'h343
`define CSR_MIP      12'h344
`define CSR_MVENDORID 12'hF11
`define CSR_MARCHID   12'hF12
`define CSR_MIMPID    12'hF13
`define CSR_MHARTID   12'hF14

//  misa pentru RV32IM: MXL=01 (32b) | I (bit8) | M (bit12)
`define MISA_RV32IM  32'h40001100

// ------------------------------------------------------------
//  Cauze de trap (mcause, bitul de interrupt = 0 pentru exceptii)
// ------------------------------------------------------------
`define CAUSE_ILLEGAL    32'd2
`define CAUSE_BREAKPOINT 32'd3
`define CAUSE_ECALL_M    32'd11

// ------------------------------------------------------------
//  Encodarea interna a operatiei ALU (semnal de control, 4 biti)
//    Nu face parte din ISA - e conventia noastra interna.
// ------------------------------------------------------------
`define ALU_OP_W     4
`define ALU_ADD      4'b0000
`define ALU_SUB      4'b0001
`define ALU_SLL      4'b0010
`define ALU_SLT      4'b0011            // set-less-than cu semn
`define ALU_SLTU     4'b0100            // set-less-than fara semn
`define ALU_XOR      4'b0101
`define ALU_SRL      4'b0110
`define ALU_SRA      4'b0111
`define ALU_OR       4'b1000
`define ALU_AND      4'b1001
`define ALU_COPY_B   4'b1010            // trece operandul B (pentru LUI)
`define ALU_NOP      4'b1111            // fara efect (bula)

// ------------------------------------------------------------
//  Selectorul de tip immediate (semnal de control, intern)
//    Spune lui imm_gen din ce format sa extraga immediate-ul.
// ------------------------------------------------------------
`define IMM_SEL_W    3
`define IMM_I        3'd0               // OP-IMM, LOAD, JALR
`define IMM_S        3'd1               // STORE
`define IMM_B        3'd2               // BRANCH
`define IMM_U        3'd3               // LUI, AUIPC
`define IMM_J        3'd4               // JAL

// ------------------------------------------------------------
//  Selectorul sursei de writeback (ce se scrie in registrul rd)
// ------------------------------------------------------------
`define WB_SEL_W     2
`define WB_ALU       2'd0               // rezultatul ALU
`define WB_MEM       2'd1               // data citita din memorie (load)
`define WB_PC4       2'd2               // PC+4 (adresa de retur, jal/jalr)

// ------------------------------------------------------------
//  Coduri pentru unitatea de forwarding (Faza 4)
//    Selecteaza sursa operandului ALU in etapa EX.
// ------------------------------------------------------------
`define FWD_NONE     2'b00              // din ID/EX (register file)
`define FWD_EXMEM    2'b10              // din EX/MEM (instr. precedenta)
`define FWD_MEMWB    2'b01              // din MEM/WB (cu 2 instr. inainte)

`endif  // RISCV_DEFS_VH

rtl/muldiv.v
`timescale 1ns / 1ps
`include "riscv_defs.vh"

// muldiv: extensia M.
// - INMULTIRE: un singur inmultitor semnat 33x33, pipeline-at (operanzi
//   inregistrati -> produs inregistrat -> selectie), ca sa fie impachetat in
//   regiitrii interni ai DSP48 si scos de pe calea critica. Acopera MUL/MULH/
//   MULHU/MULHSU prin extinderea de semn aleasa dupa operatie.
// - IMPARTIRE: iterativa, restoring (neschimbata fata de varianta verificata).
module muldiv (
    input  wire        clk,
    input  wire        rst_n,
    input  wire        stall,      // ingheata FSM (tranzactie AXI in curs)
    input  wire        start,
    input  wire [31:0] a,
    input  wire [31:0] b,
    input  wire [2:0]  op,
    output reg  [31:0] result,
    output wire        busy,
    output wire        done
);

    localparam [2:0] IDLE = 3'd0, MUL1 = 3'd1, MUL2 = 3'd2,
                     CALC = 3'd3, FIN  = 3'd4;
    reg [2:0]  state;

    // ---- registre inmultire (pipeline) ----
    reg signed [32:0] areg, breg;     // operanzi extinsi pe 33 biti, inregistrati
    reg signed [65:0] preg;           // produsul inregistrat (66 biti)
    reg               take_high_q;    // 1 = MULH*, 0 = MUL (jumatatea inferioara)

    // ---- registre impartire ----
    reg [63:0] acc;
    reg [31:0] divisor_q;
    reg [5:0]  cnt;
    reg        neg_q, neg_r;
    reg [2:0]  op_q;

    assign busy = (state == MUL1) || (state == MUL2) || (state == CALC);
    assign done = (state == FIN);

    wire is_mul = (op == `F3_MUL) || (op == `F3_MULH) ||
                  (op == `F3_MULHSU) || (op == `F3_MULHU);
    wire signed_div = (op == `F3_DIV) || (op == `F3_REM);

    // extindere de semn per operatie: a semnat la MUL/MULH/MULHSU; b semnat la MUL/MULH
    wire a_s = (op != `F3_MULHU);
    wire b_s = (op == `F3_MUL) || (op == `F3_MULH);
    wire signed [32:0] a_ext = $signed({a_s & a[31], a});
    wire signed [32:0] b_ext = $signed({b_s & b[31], b});
    wire take_high = (op != `F3_MUL);

    // pregatire impartire (valori absolute, cazuri speciale ISA)
    wire na = signed_div && a[31];
    wire nb = signed_div && b[31];
    wire [31:0] abs_a = na ? (~a + 32'd1) : a;
    wire [31:0] abs_b = nb ? (~b + 32'd1) : b;
    wire div_zero = (b == 32'd0);
    wire overflow = signed_div && (a == 32'h8000_0000) && (b == 32'hFFFF_FFFF);

    // pas impartire (restoring, 1 bit/ciclu)
    wire [63:0] acc_sh = acc << 1;
    wire [31:0] rem_hi = acc_sh[63:32];
    wire [32:0] diff   = {1'b0, rem_hi} - {1'b0, divisor_q};
    wire        ge     = ~diff[32];
    wire [63:0] acc_nx = ge ? {diff[31:0], acc_sh[31:0] | 32'h1} : acc_sh;

    always @(posedge clk or negedge rst_n) begin
        if (!rst_n) begin
            state <= IDLE; result <= 32'b0;
            areg <= 33'b0; breg <= 33'b0; preg <= 66'b0; take_high_q <= 1'b0;
            acc <= 64'b0; divisor_q <= 32'b0; cnt <= 6'b0;
            neg_q <= 1'b0; neg_r <= 1'b0; op_q <= 3'b0;
        end else if (stall) begin
            // tranzactie AXI in curs: inghetam FSM-ul (nu avansam pasii)
        end else begin
            case (state)
                IDLE: begin
                    if (start) begin
                        op_q  <= op;
                        neg_q <= (na ^ nb);
                        neg_r <= na;
                        if (is_mul) begin
                            areg <= a_ext; breg <= b_ext; take_high_q <= take_high;
                            state <= MUL1;
                        end else if (div_zero) begin
                            case (op)
                                `F3_DIV, `F3_DIVU: result <= 32'hFFFF_FFFF;
                                default:           result <= a;
                            endcase
                            state <= FIN;
                        end else if (overflow) begin
                            result <= (op == `F3_DIV) ? 32'h8000_0000 : 32'b0;
                            state  <= FIN;
                        end else begin
                            acc       <= {32'b0, abs_a};
                            divisor_q <= abs_b;
                            cnt       <= 6'd32;
                            state     <= CALC;
                        end
                    end
                end

                // inmultire pipeline: produsul intre doua registre -> DSP rapid
                MUL1: begin
                    preg  <= areg * breg;
                    state <= MUL2;
                end
                MUL2: begin
                    result <= take_high_q ? preg[63:32] : preg[31:0];
                    state  <= FIN;
                end

                CALC: begin
                    acc <= acc_nx;
                    cnt <= cnt - 6'd1;
                    if (cnt == 6'd1) begin
                        if (op_q == `F3_DIV || op_q == `F3_DIVU)
                            result <= neg_q ? (~acc_nx[31:0]  + 32'd1) : acc_nx[31:0];
                        else
                            result <= neg_r ? (~acc_nx[63:32] + 32'd1) : acc_nx[63:32];
                        state <= FIN;
                    end
                end

                FIN: state <= IDLE;

                default: state <= IDLE;
            endcase
        end
    end

endmodule

test/tb_muldiv.v
`timescale 1ns / 1ps
`include "riscv_defs.vh"
// ============================================================
//  tb_muldiv.v  -  Testbench pentru unitatea M (muldiv)
// ============================================================
`ifndef DUMP_FILE
 `define DUMP_FILE "waveform/tb_muldiv.vcd"
`endif

module tb_muldiv;

    reg         clk = 1'b0, rst_n;
    reg         start;
    reg  [31:0] a, b;
    reg  [2:0]  op;
    wire [31:0] result;
    wire        busy, done;
    integer     errors = 0;

    always #5 clk = ~clk;

    muldiv dut (.clk(clk), .rst_n(rst_n), .start(start),
                .a(a), .b(b), .op(op),
                .result(result), .busy(busy), .done(done));

    task run_op;
        input integer id;
        input [2:0]   o;
        input [31:0]  x, y, exp;
        begin
            @(negedge clk); op = o; a = x; b = y; start = 1'b1;
            @(negedge clk); start = 1'b0;
            wait (done == 1'b1);
            if (result !== exp) begin
                errors = errors + 1;
                $display("  FAIL test %0d (op=%b): got=%h exp=%h", id, o, result, exp);
            end
            @(negedge clk);
        end
    endtask

    initial begin
        $dumpfile(`DUMP_FILE);
        $dumpvars(0, tb_muldiv);
        $display("[MULDIV] pornire teste...");
        rst_n = 1'b0; start = 1'b0; a = 0; b = 0; op = 0;
        @(negedge clk); @(negedge clk); rst_n = 1'b1;

        // inmultiri
        run_op(1,  `F3_MUL,    32'd6, 32'd7, 32'd42);
        run_op(2,  `F3_MUL,    -32'd3, 32'd5, 32'hFFFFFFF1);
        run_op(3,  `F3_MULHU,  32'hFFFFFFFF, 32'hFFFFFFFF, 32'hFFFFFFFE);
        run_op(4,  `F3_MULH,   32'h80000000, 32'h80000000, 32'h40000000);
        run_op(5,  `F3_MULHSU, 32'hFFFFFFFF, 32'hFFFFFFFF, 32'hFFFFFFFF);
        // impartiri / resturi
        run_op(6,  `F3_DIV,   32'd100, 32'd7, 32'd14);
        run_op(7,  `F3_REM,   32'd100, 32'd7, 32'd2);
        run_op(8,  `F3_DIV,   -32'd100, 32'd7, -32'd14);
        run_op(9,  `F3_REM,   -32'd100, 32'd7, -32'd2);
        run_op(10, `F3_DIVU,  32'd100, 32'd7, 32'd14);
        run_op(11, `F3_REMU,  32'd100, 32'd7, 32'd2);
        // cazuri speciale
        run_op(12, `F3_DIV,   32'd5, 32'd0, 32'hFFFFFFFF);
        run_op(13, `F3_REM,   32'd5, 32'd0, 32'd5);
        run_op(14, `F3_DIVU,  32'd5, 32'd0, 32'hFFFFFFFF);
        run_op(15, `F3_REMU,  32'd5, 32'd0, 32'd5);
        run_op(16, `F3_DIV,   32'h80000000, 32'hFFFFFFFF, 32'h80000000);
        run_op(17, `F3_REM,   32'h80000000, 32'hFFFFFFFF, 32'd0);

        if (errors == 0) $display("[MULDIV] >>> PASS <<< (toate operatiile M corecte)");
        else             $display("[MULDIV] >>> FAIL <<< (%0d erori)", errors);
        $finish;
    end

endmodule

waveform/tb_muldiv.vcd
$date
	Tue Jun 23 14:22:00 2026
$end
$version
	Icarus Verilog
$end
$timescale
	1ps
$end
$scope module tb_muldiv $end
$var wire 32 ! result [31:0] $end
$var wire 1 " done $end
$var wire 1 # busy $end
$var reg 32 $ a [31:0] $end
$var reg 32 % b [31:0] $end
$var reg 1 & clk $end
$var reg 3 ' op [2:0] $end
$var reg 1 ( rst_n $end
$var reg 1 ) start $end
$var integer 32 * errors [31:0] $end
$scope module dut $end
$var wire 32 + a [31:0] $end
$var wire 32 , b [31:0] $end
$var wire 1 - b_s $end
$var wire 1 # busy $end
$var wire 1 & clk $end
$var wire 1 . ge $end
$var wire 1 / is_mul $end
$var wire 1 0 na $end
$var wire 1 1 nb $end
$var wire 3 2 op [2:0] $end
$var wire 1 3 overflow $end
$var wire 1 ( rst_n $end
$var wire 1 4 signed_div $end
$var wire 1 5 stall $end
$var wire 1 ) start $end
$var wire 1 6 take_high $end
$var wire 32 7 rem_hi [31:0] $end
$var wire 1 " done $end
$var wire 1 8 div_zero $end
$var wire 33 9 diff [32:0] $end
$var wire 33 : b_ext [32:0] $end
$var wire 64 ; acc_sh [63:0] $end
$var wire 64 < acc_nx [63:0] $end
$var wire 32 = abs_b [31:0] $end
$var wire 32 > abs_a [31:0] $end
$var wire 1 ? a_s $end
$var wire 33 @ a_ext [32:0] $end
$var parameter 3 A CALC $end
$var parameter 3 B FIN $end
$var parameter 3 C IDLE $end
$var parameter 3 D MUL1 $end
$var parameter 3 E MUL2 $end
$var reg 64 F acc [63:0] $end
$var reg 33 G areg [32:0] $end
$var reg 33 H breg [32:0] $end
$var reg 6 I cnt [5:0] $end
$var reg 32 J divisor_q [31:0] $end
$var reg 1 K neg_q $end
$var reg 1 L neg_r $end
$var reg 3 M op_q [2:0] $end
$var reg 66 N preg [65:0] $end
$var reg 32 O result [31:0] $end
$var reg 3 P state [2:0] $end
$var reg 1 Q take_high_q $end
$upscope $end
$scope task run_op $end
$var reg 32 R exp [31:0] $end
$var reg 3 S o [2:0] $end
$var reg 32 T x [31:0] $end
$var reg 32 U y [31:0] $end
$var integer 32 V id [31:0] $end
$upscope $end
$upscope $end
$enddefinitions $end
$comment Show the parameter values. $end
$dumpall
b10 E
b1 D
b0 C
b100 B
b11 A
$end
#0
$dumpvars
bx V
bx U
bx T
bx S
bx R
0Q
b0 P
b0 O
b0 N
b0 M
0L
0K
b0 J
b0 I
b0 H
b0 G
b0 F
b0 @
1?
b0 >
b0 =
b1 <
b0 ;
b0 :
b0 9
18
b0 7
06
z5
04
03
b0 2
01
00
1/
1.
1-
b0 ,
b0 +
b0 *
0)
0(
b0 '
0&
b0 %
b0 $
0#
0"
b0 !
$end
#5000
1&
#10000
0&
#15000
1&
#20000
b101010 R
b111 U
b110 T
b0 S
b1 V
1(
0&
#25000
1&
#30000
b111 =
b110 >
1)
b111 :
08
b111 %
b111 ,
b110 @
b110 $
b110 +
0&
#35000
1#
b1 P
b111 H
b110 G
1&
#40000
0)
0&
#45000
b10 P
b101010 N
1&
#50000
0&
#55000
0#
1"
b100 P
b101010 !
b101010 O
1&
#60000
b11111111111111111111111111110001 R
b101 U
b11111111111111111111111111111101 T
b10 V
0&
#65000
0"
b0 P
1&
#70000
b101 =
b11111111111111111111111111111101 >
1)
b101 :
b101 %
b101 ,
b111111111111111111111111111111101 @
b11111111111111111111111111111101 $
b11111111111111111111111111111101 +
0&
#75000
1#
b1 P
b101 H
b111111111111111111111111111111101 G
1&
#80000
0)
0&
#85000
b10 P
b111111111111111111111111111111111111111111111111111111111111110001 N
1&
#90000
0&
#95000
0#
1"
b100 P
b11111111111111111111111111110001 !
b11111111111111111111111111110001 O
1&
#100000
b11111111111111111111111111111110 R
b11111111111111111111111111111111 U
b11111111111111111111111111111111 T
b11 S
b11 V
0&
#105000
0"
b0 P
1&
#110000
b11111111111111111111111111111111 =
b11111111111111111111111111111111 >
0-
1)
b11111111111111111111111111111111 :
b11111111111111111111111111111111 %
b11111111111111111111111111111111 ,
b11111111111111111111111111111111 @
b11111111111111111111111111111111 $
b11111111111111111111111111111111 +
0?
16
b11 '
b11 2
0&
#115000
1#
b1 P
1Q
b11111111111111111111111111111111 H
b11111111111111111111111111111111 G
b11 M
1&
#120000
0)
0&
#125000
b10 P
b1111111111111111111111111111111000000000000000000000000000000001 N
1&
#130000
0&
#135000
0#
1"
b100 P
b11111111111111111111111111111110 !
b11111111111111111111111111111110 O
1&
#140000
b1000000000000000000000000000000 R
b10000000000000000000000000000000 U
b10000000000000000000000000000000 T
b1 S
b100 V
0&
#145000
0"
b0 P
1&
#150000
b10000000000000000000000000000000 =
b10000000000000000000000000000000 >
1/
1-
1)
b110000000000000000000000000000000 :
b10000000000000000000000000000000 %
b10000000000000000000000000000000 ,
b110000000000000000000000000000000 @
b10000000000000000000000000000000 $
b10000000000000000000000000000000 +
1?
b1 '
b1 2
0&
#155000
1#
b1 P
b110000000000000000000000000000000 H
b110000000000000000000000000000000 G
b1 M
1&
#160000
0)
0&
#165000
b10 P
b100000000000000000000000000000000000000000000000000000000000000 N
1&
#170000
0&
#175000
0#
1"
b100 P
b1000000000000000000000000000000 !
b1000000000000000000000000000000 O
1&
#180000
b11111111111111111111111111111111 R
b11111111111111111111111111111111 U
b11111111111111111111111111111111 T
b10 S
b101 V
0&
#185000
0"
b0 P
1&
#190000
b11111111111111111111111111111111 =
b11111111111111111111111111111111 >
0-
1)
b11111111111111111111111111111111 :
b11111111111111111111111111111111 %
b11111111111111111111111111111111 ,
b111111111111111111111111111111111 @
b11111111111111111111111111111111 $
b11111111111111111111111111111111 +
b10 '
b10 2
0&
#195000
1#
b1 P
b11111111111111111111111111111111 H
b111111111111111111111111111111111 G
b10 M
1&
#200000
0)
0&
#205000
b10 P
b111111111111111111111111111111111100000000000000000000000000000001 N
1&
#210000
0&
#215000
0#
1"
b100 P
b11111111111111111111111111111111 !
b11111111111111111111111111111111 O
1&
#220000
b1110 R
b111 U
b1100100 T
b100 S
b110 V
0&
#225000
0"
b0 P
1&
#230000
0/
b111 =
b1100100 >
14
1)
b111 :
b111 %
b111 ,
b1100100 @
b1100100 $
b1100100 +
b100 '
b100 2
0&
#235000
0.
b11001000 <
1#
b11001000 ;
b11 P
b100000 I
b111111111111111111111111111111001 9
b111 J
b1100100 F
b100 M
1&
#240000
0)
0&
#245000
b110010000 <
b110010000 ;
b11111 I
b11001000 F
1&
#250000
0&
#255000
b1100100000 <
b1100100000 ;
b11110 I
b110010000 F
1&
#260000
0&
#265000
b11001000000 <
b11001000000 ;
b11101 I
b1100100000 F
1&
#270000
0&
#275000
b110010000000 <
b110010000000 ;
b11100 I
b11001000000 F
1&
#280000
0&
#285000
b1100100000000 <
b1100100000000 ;
b11011 I
b110010000000 F
1&
#290000
0&
#295000
b11001000000000 <
b11001000000000 ;
b11010 I
b1100100000000 F
1&
#300000
0&
#305000
b110010000000000 <
b110010000000000 ;
b11001 I
b11001000000000 F
1&
#310000
0&
#315000
b1100100000000000 <
b1100100000000000 ;
b11000 I
b110010000000000 F
1&
#320000
0&
#325000
b11001000000000000 <
b11001000000000000 ;
b10111 I
b1100100000000000 F
1&
#330000
0&
#335000
b110010000000000000 <
b110010000000000000 ;
b10110 I
b11001000000000000 F
1&
#340000
0&
#345000
b1100100000000000000 <
b1100100000000000000 ;
b10101 I
b110010000000000000 F
1&
#350000
0&
#355000
b11001000000000000000 <
b11001000000000000000 ;
b10100 I
b1100100000000000000 F
1&
#360000
0&
#365000
b110010000000000000000 <
b110010000000000000000 ;
b10011 I
b11001000000000000000 F
1&
#370000
0&
#375000
b1100100000000000000000 <
b1100100000000000000000 ;
b10010 I
b110010000000000000000 F
1&
#380000
0&
#385000
b11001000000000000000000 <
b11001000000000000000000 ;
b10001 I
b1100100000000000000000 F
1&
#390000
0&
#395000
b110010000000000000000000 <
b110010000000000000000000 ;
b10000 I
b11001000000000000000000 F
1&
#400000
0&
#405000
b1100100000000000000000000 <
b1100100000000000000000000 ;
b1111 I
b110010000000000000000000 F
1&
#410000
0&
#415000
b11001000000000000000000000 <
b11001000000000000000000000 ;
b1110 I
b1100100000000000000000000 F
1&
#420000
0&
#425000
b110010000000000000000000000 <
b110010000000000000000000000 ;
b1101 I
b11001000000000000000000000 F
1&
#430000
0&
#435000
b1100100000000000000000000000 <
b1100100000000000000000000000 ;
b1100 I
b110010000000000000000000000 F
1&
#440000
0&
#445000
b11001000000000000000000000000 <
b11001000000000000000000000000 ;
b1011 I
b1100100000000000000000000000 F
1&
#450000
0&
#455000
b110010000000000000000000000000 <
b110010000000000000000000000000 ;
b1010 I
b11001000000000000000000000000 F
1&
#460000
0&
#465000
b1100100000000000000000000000000 <
b1100100000000000000000000000000 ;
b1001 I
b110010000000000000000000000000 F
1&
#470000
0&
#475000
b11001000000000000000000000000000 <
b11001000000000000000000000000000 ;
b1000 I
b1100100000000000000000000000000 F
1&
#480000
0&
#485000
b111111111111111111111111111111010 9
b1 7
b110010000000000000000000000000000 <
b110010000000000000000000000000000 ;
b111 I
b11001000000000000000000000000000 F
1&
#490000
0&
#495000
b111111111111111111111111111111100 9
b11 7
b1100100000000000000000000000000000 <
b1100100000000000000000000000000000 ;
b110 I
b110010000000000000000000000000000 F
1&
#500000
0&
#505000
b111111111111111111111111111111111 9
b110 7
b11001000000000000000000000000000000 <
b11001000000000000000000000000000000 ;
b101 I
b1100100000000000000000000000000000 F
1&
#510000
0&
#515000
1.
b101 9
b1100 7
b10110000000000000000000000000000001 <
b110010000000000000000000000000000000 ;
b100 I
b11001000000000000000000000000000000 F
1&
#520000
0&
#525000
b10000000000000000000000000000000011 <
b100 9
b1011 7
b101100000000000000000000000000000010 ;
b11 I
b10110000000000000000000000000000001 F
1&
#530000
0&
#535000
b100000000000000000000000000000111 <
b1 9
b1000 7
b100000000000000000000000000000000110 ;
b10 I
b10000000000000000000000000000000011 F
1&
#540000
0&
#545000
0.
b1000000000000000000000000000001110 <
b111111111111111111111111111111011 9
b10 7
b1000000000000000000000000000001110 ;
b1 I
b100000000000000000000000000000111 F
1&
#550000
0&
#555000
b111111111111111111111111111111101 9
b100 7
b10000000000000000000000000000011100 <
0#
b10000000000000000000000000000011100 ;
1"
b100 P
b1110 !
b1110 O
b0 I
b1000000000000000000000000000001110 F
1&
#560000
b10 R
b110 S
b111 V
0&
#565000
0"
b0 P
1&
#570000
1)
b110 '
b110 2
0&
#575000
b111111111111111111111111111111001 9
b0 7
b11001000 <
1#
b11001000 ;
b11 P
b100000 I
b1100100 F
b110 M
1&
#580000
0)
0&
#585000
b110010000 <
b110010000 ;
b11111 I
b11001000 F
1&
#590000
0&
#595000
b1100100000 <
b1100100000 ;
b11110 I
b110010000 F
1&
#600000
0&
#605000
b11001000000 <
b11001000000 ;
b11101 I
b1100100000 F
1&
#610000
0&
#615000
b110010000000 <
b110010000000 ;
b11100 I
b11001000000 F
1&
#620000
0&
#625000
b1100100000000 <
b1100100000000 ;
b11011 I
b110010000000 F
1&
#630000
0&
#635000
b11001000000000 <
b11001000000000 ;
b11010 I
b1100100000000 F
1&
#640000
0&
#645000
b110010000000000 <
b110010000000000 ;
b11001 I
b11001000000000 F
1&
#650000
0&
#655000
b1100100000000000 <
b1100100000000000 ;
b11000 I
b110010000000000 F
1&
#660000
0&
#665000
b11001000000000000 <
b11001000000000000 ;
b10111 I
b1100100000000000 F
1&
#670000
0&
#675000
b110010000000000000 <
b110010000000000000 ;
b10110 I
b11001000000000000 F
1&
#680000
0&
#685000
b1100100000000000000 <
b1100100000000000000 ;
b10101 I
b110010000000000000 F
1&
#690000
0&
#695000
b11001000000000000000 <
b11001000000000000000 ;
b10100 I
b1100100000000000000 F
1&
#700000
0&
#705000
b110010000000000000000 <
b110010000000000000000 ;
b10011 I
b11001000000000000000 F
1&
#710000
0&
#715000
b1100100000000000000000 <
b1100100000000000000000 ;
b10010 I
b110010000000000000000 F
1&
#720000
0&
#725000
b11001000000000000000000 <
b11001000000000000000000 ;
b10001 I
b1100100000000000000000 F
1&
#730000
0&
#735000
b110010000000000000000000 <
b110010000000000000000000 ;
b10000 I
b11001000000000000000000 F
1&
#740000
0&
#745000
b1100100000000000000000000 <
b1100100000000000000000000 ;
b1111 I
b110010000000000000000000 F
1&
#750000
0&
#755000
b11001000000000000000000000 <
b11001000000000000000000000 ;
b1110 I
b1100100000000000000000000 F
1&
#760000
0&
#765000
b110010000000000000000000000 <
b110010000000000000000000000 ;
b1101 I
b11001000000000000000000000 F
1&
#770000
0&
#775000
b1100100000000000000000000000 <
b1100100000000000000000000000 ;
b1100 I
b110010000000000000000000000 F
1&
#780000
0&
#785000
b11001000000000000000000000000 <
b11001000000000000000000000000 ;
b1011 I
b1100100000000000000000000000 F
1&
#790000
0&
#795000
b110010000000000000000000000000 <
b110010000000000000000000000000 ;
b1010 I
b11001000000000000000000000000 F
1&
#800000
0&
#805000
b1100100000000000000000000000000 <
b1100100000000000000000000000000 ;
b1001 I
b110010000000000000000000000000 F
1&
#810000
0&
#815000
b11001000000000000000000000000000 <
b11001000000000000000000000000000 ;
b1000 I
b1100100000000000000000000000000 F
1&
#820000
0&
#825000
b111111111111111111111111111111010 9
b1 7
b110010000000000000000000000000000 <
b110010000000000000000000000000000 ;
b111 I
b11001000000000000000000000000000 F
1&
#830000
0&
#835000
b111111111111111111111111111111100 9
b11 7
b1100100000000000000000000000000000 <
b1100100000000000000000000000000000 ;
b110 I
b110010000000000000000000000000000 F
1&
#840000
0&
#845000
b111111111111111111111111111111111 9
b110 7
b11001000000000000000000000000000000 <
b11001000000000000000000000000000000 ;
b101 I
b1100100000000000000000000000000000 F
1&
#850000
0&
#855000
1.
b101 9
b1100 7
b10110000000000000000000000000000001 <
b110010000000000000000000000000000000 ;
b100 I
b11001000000000000000000000000000000 F
1&
#860000
0&
#865000
b10000000000000000000000000000000011 <
b100 9
b1011 7
b101100000000000000000000000000000010 ;
b11 I
b10110000000000000000000000000000001 F
1&
#870000
0&
#875000
b100000000000000000000000000000111 <
b1 9
b1000 7
b100000000000000000000000000000000110 ;
b10 I
b10000000000000000000000000000000011 F
1&
#880000
0&
#885000
0.
b1000000000000000000000000000001110 <
b111111111111111111111111111111011 9
b10 7
b1000000000000000000000000000001110 ;
b1 I
b100000000000000000000000000000111 F
1&
#890000
0&
#895000
b111111111111111111111111111111101 9
b100 7
b10000000000000000000000000000011100 <
0#
b10000000000000000000000000000011100 ;
1"
b100 P
b10 !
b10 O
b0 I
b1000000000000000000000000000001110 F
1&
#900000
b11111111111111111111111111110010 R
b11111111111111111111111110011100 T
b100 S
b1000 V
0&
#905000
0"
b0 P
1&
#910000
10
b1100100 >
1)
b111111111111111111111111110011100 @
b11111111111111111111111110011100 $
b11111111111111111111111110011100 +
b100 '
b100 2
0&
#915000
b111111111111111111111111111111001 9
b0 7
b11001000 <
1#
b11001000 ;
b11 P
b100000 I
b1100100 F
1L
1K
b100 M
1&
#920000
0)
0&
#925000
b110010000 <
b110010000 ;
b11111 I
b11001000 F
1&
#930000
0&
#935000
b1100100000 <
b1100100000 ;
b11110 I
b110010000 F
1&
#940000
0&
#945000
b11001000000 <
b11001000000 ;
b11101 I
b1100100000 F
1&
#950000
0&
