rtl/riscv_defs.vh
`ifndef RISCV_DEFS_VH
`define RISCV_DEFS_VH

// ------------------------------------------------------------
//  Parametri generali
// ------------------------------------------------------------
`define XLEN         32                 // latimea cuvantului
`define RV_NOP       32'h0000_0013      // addi x0, x0, 0  (bula in pipeline)
`define RESET_PC     32'h0000_0000      // adresa de start dupa reset

// ------------------------------------------------------------
//  Extractoare de campuri din instructiune (i = vector 32-bit)
//    Formate RISC-V:
//      R: funct7 | rs2 | rs1 | funct3 | rd | opcode
//      I: imm[11:0]       | rs1 | funct3 | rd | opcode
//      S: imm[11:5] | rs2 | rs1 | funct3 | imm[4:0] | opcode
//      B: imm[12|10:5]|rs2|rs1|funct3| imm[4:1|11] | opcode
//      U: imm[31:12]                  | rd | opcode
//      J: imm[20|10:1|11|19:12]       | rd | opcode
// ------------------------------------------------------------
`define OPCODE(i)    (i[6:0])
`define RD(i)        (i[11:7])
`define RS1(i)       (i[19:15])
`define RS2(i)       (i[24:20])
`define FUNCT3(i)    (i[14:12])
`define FUNCT7(i)    (i[31:25])

// ------------------------------------------------------------
//  Opcode-uri (bitii [6:0])
// ------------------------------------------------------------
`define OPC_LUI      7'b0110111         // U  - load upper immediate
`define OPC_AUIPC    7'b0010111         // U  - add upper imm to PC
`define OPC_JAL      7'b1101111         // J  - jump and link
`define OPC_JALR     7'b1100111         // I  - jump and link register
`define OPC_BRANCH   7'b1100011         // B  - branch conditionat
`define OPC_LOAD     7'b0000011         // I  - load din memorie
`define OPC_STORE    7'b0100011         // S  - store in memorie
`define OPC_OP_IMM   7'b0010011         // I  - ALU cu immediate
`define OPC_OP       7'b0110011         // R  - ALU cu registre (+ extensia M)
`define OPC_MISC_MEM 7'b0001111         // I  - FENCE
`define OPC_SYSTEM   7'b1110011         // I  - ECALL/EBREAK/CSR

// ------------------------------------------------------------
//  funct3 pentru OP / OP-IMM (aritmetica/logica)
//    SUB vs ADD si SRA vs SRL se disting prin bitul funct7[5] (=i[30])
// ------------------------------------------------------------
`define F3_ADD_SUB   3'b000             // ADD/ADDI ; SUB (funct7[5]=1)
`define F3_SLL       3'b001             // shift left logic
`define F3_SLT       3'b010             // set less than (cu semn)
`define F3_SLTU      3'b011             // set less than (fara semn)
`define F3_XOR       3'b100
`define F3_SRL_SRA   3'b101             // SRL ; SRA (funct7[5]=1)
`define F3_OR        3'b110
`define F3_AND       3'b111

// ------------------------------------------------------------
//  funct3 pentru BRANCH
// ------------------------------------------------------------
`define F3_BEQ       3'b000
`define F3_BNE       3'b001
`define F3_BLT       3'b100
`define F3_BGE       3'b101
`define F3_BLTU      3'b110
`define F3_BGEU      3'b111

// ------------------------------------------------------------
//  funct3 pentru LOAD / STORE (dimensiunea accesului)
// ------------------------------------------------------------
`define F3_LB        3'b000             // load byte (cu semn)
`define F3_LH        3'b001             // load half (cu semn)
`define F3_LW        3'b010             // load word
`define F3_LBU       3'b100             // load byte (fara semn)
`define F3_LHU       3'b101             // load half (fara semn)

`define F3_SB        3'b000             // store byte
`define F3_SH        3'b001             // store half
`define F3_SW        3'b010             // store word

// ------------------------------------------------------------
//  funct7 relevante
// ------------------------------------------------------------
`define F7_BASE      7'b0000000         // ADD, SRL, AND, ...
`define F7_ALT       7'b0100000         // SUB, SRA  (bitul [5]=1)
`define F7_MULDIV    7'b0000001         // extensia M
`define F7_BIT5      30                 // pozitia bitului ALT in instructiune

// ------------------------------------------------------------
//  Extensia M (opcode OPC_OP, funct7 = F7_MULDIV), prin funct3
// ------------------------------------------------------------
`define F3_MUL       3'b000             // produs, 32 bitii inferiori
`define F3_MULH      3'b001             // produs sup., semnat x semnat
`define F3_MULHSU    3'b010             // produs sup., semnat x nesemnat
`define F3_MULHU     3'b011             // produs sup., nesemnat x nesemnat
`define F3_DIV       3'b100             // impartire cu semn
`define F3_DIVU      3'b101             // impartire fara semn
`define F3_REM       3'b110             // rest cu semn
`define F3_REMU      3'b111             // rest fara semn

// ------------------------------------------------------------
//  funct3 pentru SYSTEM (ECALL/EBREAK + CSR)
// ------------------------------------------------------------
`define F3_PRIV      3'b000             // ECALL/EBREAK (dupa funct12)
`define F3_CSRRW     3'b001
`define F3_CSRRS     3'b010
`define F3_CSRRC     3'b011
`define F3_CSRRWI    3'b101
`define F3_CSRRSI    3'b110
`define F3_CSRRCI    3'b111

// ------------------------------------------------------------
//  funct12 (instr[31:20]) pentru SYSTEM cu funct3=000
// ------------------------------------------------------------
`define SYS_ECALL    12'h000
`define SYS_EBREAK   12'h001
`define SYS_MRET     12'h302

// ------------------------------------------------------------
//  Adrese CSR (mod masina) - subset minim pentru Zicsr + trap
// ------------------------------------------------------------
`define CSR_MSTATUS  12'h300
`define CSR_MISA     12'h301
`define CSR_MIE      12'h304
`define CSR_MTVEC    12'h305
`define CSR_MSCRATCH 12'h340
`define CSR_MEPC     12'h341
`define CSR_MCAUSE   12'h342
`define CSR_MTVAL    12'h343
`define CSR_MIP      12'h344
`define CSR_MVENDORID 12'hF11
`define CSR_MARCHID   12'hF12
`define CSR_MIMPID    12'hF13
`define CSR_MHARTID   12'hF14

//  misa pentru RV32IM: MXL=01 (32b) | I (bit8) | M (bit12)
`define MISA_RV32IM  32'h40001100

// ------------------------------------------------------------
//  Cauze de trap (mcause, bitul de interrupt = 0 pentru exceptii)
// ------------------------------------------------------------
`define CAUSE_ILLEGAL    32'd2
`define CAUSE_BREAKPOINT 32'd3
`define CAUSE_ECALL_M    32'd11

// ------------------------------------------------------------
//  Encodarea interna a operatiei ALU (semnal de control, 4 biti)
//    Nu face parte din ISA - e conventia noastra interna.
// ------------------------------------------------------------
`define ALU_OP_W     4
`define ALU_ADD      4'b0000
`define ALU_SUB      4'b0001
`define ALU_SLL      4'b0010
`define ALU_SLT      4'b0011            // set-less-than cu semn
`define ALU_SLTU     4'b0100            // set-less-than fara semn
`define ALU_XOR      4'b0101
`define ALU_SRL      4'b0110
`define ALU_SRA      4'b0111
`define ALU_OR       4'b1000
`define ALU_AND      4'b1001
`define ALU_COPY_B   4'b1010            // trece operandul B (pentru LUI)
`define ALU_NOP      4'b1111            // fara efect (bula)

// ------------------------------------------------------------
//  Selectorul de tip immediate (semnal de control, intern)
//    Spune lui imm_gen din ce format sa extraga immediate-ul.
// ------------------------------------------------------------
`define IMM_SEL_W    3
`define IMM_I        3'd0               // OP-IMM, LOAD, JALR
`define IMM_S        3'd1               // STORE
`define IMM_B        3'd2               // BRANCH
`define IMM_U        3'd3               // LUI, AUIPC
`define IMM_J        3'd4               // JAL

// ------------------------------------------------------------
//  Selectorul sursei de writeback (ce se scrie in registrul rd)
// ------------------------------------------------------------
`define WB_SEL_W     2
`define WB_ALU       2'd0               // rezultatul ALU
`define WB_MEM       2'd1               // data citita din memorie (load)
`define WB_PC4       2'd2               // PC+4 (adresa de retur, jal/jalr)

// ------------------------------------------------------------
//  Coduri pentru unitatea de forwarding (Faza 4)
//    Selecteaza sursa operandului ALU in etapa EX.
// ------------------------------------------------------------
`define FWD_NONE     2'b00              // din ID/EX (register file)
`define FWD_EXMEM    2'b10              // din EX/MEM (instr. precedenta)
`define FWD_MEMWB    2'b01              // din MEM/WB (cu 2 instr. inainte)

`endif  // RISCV_DEFS_VH

rtl/regfile.v
`timescale 1ns / 1ps
`include "riscv_defs.vh"

module regfile (
    input  wire              clk,
    input  wire              we,
    input  wire [4:0]        rd_addr,
    input  wire [`XLEN-1:0]  rd_data,
    input  wire [4:0]        rs1_addr,
    input  wire [4:0]        rs2_addr,
    output wire [`XLEN-1:0]  rs1_data,
    output wire [`XLEN-1:0]  rs2_data
);
    (* ram_style = "distributed" *)
    reg [`XLEN-1:0] regs [0:31];

    integer i;
    initial for (i = 0; i < 32; i = i + 1) regs[i] = {`XLEN{1'b0}};

    // scriere sincrona; x0 (rd_addr==0) nu se scrie niciodata
    always @(posedge clk)
        if (we && (rd_addr != 5'd0))
            regs[rd_addr] <= rd_data;

    // citire combinationala; x0 fortat la 0
    assign rs1_data = (rs1_addr == 5'd0) ? {`XLEN{1'b0}} : regs[rs1_addr];
    assign rs2_data = (rs2_addr == 5'd0) ? {`XLEN{1'b0}} : regs[rs2_addr];
endmodule

test/tb_regfile.v
`timescale 1ns/1ps
`include "riscv_defs.vh"

`ifndef DUMP_FILE
 `define DUMP_FILE "waveform/tb_regfile.vcd"
`endif

module tb_regfile;

    reg               clk = 1'b0;
    reg               we;
    reg  [4:0]        rd_addr, rs1_addr, rs2_addr;
    reg  [`XLEN-1:0]  rd_data;
    wire [`XLEN-1:0]  rs1_data, rs2_data;
    integer           errors = 0;

    always #5 clk = ~clk;   // ceas 100 MHz

    regfile dut (
        .clk(clk),
        .we(we), .rd_addr(rd_addr), .rd_data(rd_data),
        .rs1_addr(rs1_addr), .rs2_addr(rs2_addr),
        .rs1_data(rs1_data), .rs2_data(rs2_data)
    );

    // scrie val in registrul addr (stimul aliniat pe negedge -> scriere pe posedge)
    task write_reg;
        input [4:0]       addr;
        input [`XLEN-1:0] val;
        begin
            @(negedge clk); we = 1'b1; rd_addr = addr; rd_data = val;
            @(negedge clk); we = 1'b0;
        end
    endtask

    task chk;
        input integer        id;
        input [`XLEN-1:0]    got;
        input [`XLEN-1:0]    exp;
        begin
            if (got !== exp) begin
                errors = errors + 1;
                $display("  FAIL test %0d: got=%h exp=%h", id, got, exp);
            end
        end
    endtask

    initial begin
        $dumpfile(`DUMP_FILE);
        $dumpvars(0, tb_regfile);
        $display("[REGFILE] pornire teste...");

        // --- la initializare, registrele sunt 0 (bloc initial) ---
        we = 1'b0; rd_addr = 0; rd_data = 0;
        rs1_addr = 5'd5; rs2_addr = 5'd6;
        @(negedge clk);
        chk(1, rs1_data, 32'd0);          // la initializare, x5 = 0

        // --- scriere/citire x5 ---
        write_reg(5'd5, 32'hDEADBEEF);
        rs1_addr = 5'd5; #1;
        chk(2, rs1_data, 32'hDEADBEEF);

        // --- al doilea port de citire, x6 ---
        write_reg(5'd6, 32'h12345678);
        rs2_addr = 5'd6; #1;
        chk(3, rs2_data, 32'h12345678);

        // --- x0 ramane 0 chiar daca incercam sa scriem in el ---
        write_reg(5'd0, 32'hFFFFFFFF);
        rs1_addr = 5'd0; #1;
        chk(4, rs1_data, 32'd0);

        // --- citiri simultane independente ---
        rs1_addr = 5'd5; rs2_addr = 5'd6; #1;
        chk(5, rs1_data, 32'hDEADBEEF);
        chk(6, rs2_data, 32'h12345678);

        if (errors==0) $display("[REGFILE] >>> PASS <<< (scriere/citire/x0 corecte)");
        else           $display("[REGFILE] >>> FAIL <<< (%0d erori)", errors);
        $finish;
    end

endmodule

waveform/tb_regfile.vcd
$date
	Tue Jun 23 14:22:00 2026
$end
$version
	Icarus Verilog
$end
$timescale
	1ps
$end
$scope module tb_regfile $end
$var wire 32 ! rs2_data [31:0] $end
$var wire 32 " rs1_data [31:0] $end
$var reg 1 # clk $end
$var reg 5 $ rd_addr [4:0] $end
$var reg 32 % rd_data [31:0] $end
$var reg 5 & rs1_addr [4:0] $end
$var reg 5 ' rs2_addr [4:0] $end
$var reg 1 ( we $end
$var integer 32 ) errors [31:0] $end
$scope module dut $end
$var wire 1 # clk $end
$var wire 5 * rd_addr [4:0] $end
$var wire 32 + rd_data [31:0] $end
$var wire 5 , rs1_addr [4:0] $end
$var wire 5 - rs2_addr [4:0] $end
$var wire 1 ( we $end
$var wire 32 . rs2_data [31:0] $end
$var wire 32 / rs1_data [31:0] $end
$var integer 32 0 i [31:0] $end
$upscope $end
$scope task chk $end
$var reg 32 1 exp [31:0] $end
$var reg 32 2 got [31:0] $end
$var integer 32 3 id [31:0] $end
$upscope $end
$scope task write_reg $end
$var reg 5 4 addr [4:0] $end
$var reg 32 5 val [31:0] $end
$upscope $end
$upscope $end
$enddefinitions $end
$comment Show the parameter values. $end
$dumpall
$end
#0
$dumpvars
bx 5
bx 4
bx 3
bx 2
bx 1
b100000 0
b0 /
b0 .
b110 -
b101 ,
b0 +
b0 *
b0 )
0(
b110 '
b101 &
b0 %
b0 $
0#
b0 "
b0 !
$end
#5000
1#
#10000
b11011110101011011011111011101111 5
b101 4
b0 1
b0 2
b1 3
0#
#15000
1#
#20000
b11011110101011011011111011101111 %
b11011110101011011011111011101111 +
b101 $
b101 *
1(
0#
#25000
b11011110101011011011111011101111 "
b11011110101011011011111011101111 /
1#
#30000
0(
0#
#31000
b10010001101000101011001111000 5
b110 4
b11011110101011011011111011101111 1
b11011110101011011011111011101111 2
b10 3
#35000
1#
#40000
b10010001101000101011001111000 %
b10010001101000101011001111000 +
b110 $
b110 *
1(
0#
#45000
b10010001101000101011001111000 !
b10010001101000101011001111000 .
1#
#50000
0(
0#
#51000
b11111111111111111111111111111111 5
b0 4
b10010001101000101011001111000 1
b10010001101000101011001111000 2
b11 3
#55000
1#
#60000
b11111111111111111111111111111111 %
b11111111111111111111111111111111 +
b0 $
b0 *
1(
0#
#65000
1#
#70000
b0 "
b0 /
b0 &
b0 ,
0(
0#
#71000
b11011110101011011011111011101111 "
b11011110101011011011111011101111 /
b101 &
b101 ,
b0 1
b0 2
b100 3
#72000
b10010001101000101011001111000 1
b10010001101000101011001111000 2
b110 3
