test/tb_sanity.v
`timescale 1ns/1ps
// ============================================================
//  tb_sanity.v  -  Test minimal pentru verificarea toolchain-ului
// ------------------------------------------------------------
//  Confirma ca iverilog + vvp compileaza/ruleaza si ca scrierea
//  formei de unda (VCD pentru GTKWave) merge. Nu testeaza CPU-ul.
// ============================================================

// Numele fisierului VCD vine din Makefile (-D DUMP_FILE). Fallback local:
`ifndef DUMP_FILE
 `define DUMP_FILE "waveform/tb_sanity.vcd"
`endif

module tb_sanity;

    reg        clk = 1'b0;
    reg  [7:0] count = 8'd0;

    always #5 clk = ~clk;            // ceas 100 MHz (perioada 10 ns)

    always @(posedge clk)
        count <= count + 8'd1;

    initial begin
        $dumpfile(`DUMP_FILE);
        $dumpvars(0, tb_sanity);

        $display("[SANITY] Toolchain Icarus pornit. Numar 10 fronturi de ceas...");
        #100;
        $display("[SANITY] count = %0d (asteptat: 10)", count);
        if (count == 8'd10) $display("[SANITY] >>> PASS <<<");
        else                $display("[SANITY] >>> FAIL <<<");
        $finish;
    end

endmodule

waveform/tb_sanity.vcd
$date
	Thu Jun 11 04:51:18 2026
$end
$version
	Icarus Verilog
$end
$timescale
	1ps
$end
$scope module tb_sanity $end
$var reg 1 ! clk $end
$var reg 8 " count [7:0] $end
$upscope $end
$enddefinitions $end
$comment Show the parameter values. $end
$dumpall
$end
#0
$dumpvars
b0 "
0!
$end
#5000
b1 "
1!
#10000
0!
#15000
b10 "
1!
#20000
0!
#25000
b11 "
1!
#30000
0!
#35000
b100 "
1!
#40000
0!
#45000
b101 "
1!
#50000
0!
#55000
b110 "
1!
#60000
0!
#65000
b111 "
1!
#70000
0!
#75000
b1000 "
1!
#80000
0!
#85000
b1001 "
1!
#90000
0!
#95000
b1010 "
1!
